{
  "id": "AVD-GCP-0012",
  "apiVersion": 2,
  "version": 1,
  "title": "Disable project-wide SSH keys for all instances",
  "description": "Use of project-wide SSH keys means that a compromise of any one of these key pairs can result in all instances being compromised. It is recommended to use instance-level keys.",
  "custom": {
    "severity": "MEDIUM",
    "possibleImpact": "Compromise of a single key pair compromises all instances",
    "references": [],
    "apis": [],
    "refs": {
      "cfsec": [],
      "cspm": [
        {
          "id": -1,
          "name": "TODO-CSPM-PLUGIN-NAME"
        }
      ],
      "tfsec": [
        "google-compute-no-project-wide-ssh-keys"
      ]
    }
  }
}